{
  "cover": {
    "frankenfit_version": {
      "output_type": "display_data",
      "metadata": {
        "scrapbook": {
          "name": "frankenfit_version",
          "mime_prefix": ""
        }
      },
      "data": {
        "text/plain": "'0.1.dev1+g030dd60'"
      }
    },
    "build_time": {
      "output_type": "display_data",
      "metadata": {
        "scrapbook": {
          "name": "build_time",
          "mime_prefix": ""
        }
      },
      "data": {
        "text/plain": "'2023-01-27 23:56 UTC'"
      }
    }
  },
  "synopsis": {
    "how_parallel": {
      "output_type": "display_data",
      "metadata": {
        "scrapbook": {
          "name": "how_parallel",
          "mime_prefix": ""
        }
      },
      "data": {
        "text/plain": "105"
      }
    }
  }
}